code_blocks/apps.py
code_blocks/blocks/__init__.py
code_blocks/blocks/pygments/__init__.py
code_blocks/blocks/pygments/adapter.py
code_blocks/blocks/pygments/block.py
code_blocks/management/commands/gen_pygments_style_css.py
code_blocks/static/code_blocks/css/admin/pygments_code_block.css
code_blocks/static/code_blocks/css/pygments/abap.css
code_blocks/static/code_blocks/css/pygments/algol.css
code_blocks/static/code_blocks/css/pygments/algol_nu.css
code_blocks/static/code_blocks/css/pygments/arduino.css
code_blocks/static/code_blocks/css/pygments/autumn.css
code_blocks/static/code_blocks/css/pygments/borland.css
code_blocks/static/code_blocks/css/pygments/bw.css
code_blocks/static/code_blocks/css/pygments/colorful.css
code_blocks/static/code_blocks/css/pygments/default.css
code_blocks/static/code_blocks/css/pygments/dracula.css
code_blocks/static/code_blocks/css/pygments/emacs.css
code_blocks/static/code_blocks/css/pygments/friendly.css
code_blocks/static/code_blocks/css/pygments/friendly_grayscale.css
code_blocks/static/code_blocks/css/pygments/fruity.css
code_blocks/static/code_blocks/css/pygments/github-dark.css
code_blocks/static/code_blocks/css/pygments/gruvbox-dark.css
code_blocks/static/code_blocks/css/pygments/gruvbox-light.css
code_blocks/static/code_blocks/css/pygments/igor.css
code_blocks/static/code_blocks/css/pygments/inkpot.css
code_blocks/static/code_blocks/css/pygments/lightbulb.css
code_blocks/static/code_blocks/css/pygments/lilypond.css
code_blocks/static/code_blocks/css/pygments/lovelace.css
code_blocks/static/code_blocks/css/pygments/manni.css
code_blocks/static/code_blocks/css/pygments/material.css
code_blocks/static/code_blocks/css/pygments/monokai.css
code_blocks/static/code_blocks/css/pygments/murphy.css
code_blocks/static/code_blocks/css/pygments/native.css
code_blocks/static/code_blocks/css/pygments/nord-darker.css
code_blocks/static/code_blocks/css/pygments/nord.css
code_blocks/static/code_blocks/css/pygments/one-dark.css
wagtail_code_blocks-0.2.0.dist-info/METADATA
wagtail_code_blocks-0.2.0.dist-info/WHEEL
wagtail_code_blocks-0.2.0.dist-info/RECORD
